cm3/__init__.py
cm3/model.py
cm3/utils/__init__.py
cm3/utils/stable_adamw.py
cm3-0.2.9.dist-info/LICENSE
cm3-0.2.9.dist-info/WHEEL
cm3-0.2.9.dist-info/METADATA
cm3-0.2.9.dist-info/RECORD
